odoo/addons/website_megamenu/README.rst
odoo/addons/website_megamenu/__init__.py
odoo/addons/website_megamenu/__manifest__.py
odoo/addons/website_megamenu/i18n/es.po
odoo/addons/website_megamenu/i18n/website_megamenu.pot
odoo/addons/website_megamenu/models/__init__.py
odoo/addons/website_megamenu/models/website_menu.py
odoo/addons/website_megamenu/readme/CONTRIBUTORS.rst
odoo/addons/website_megamenu/readme/CREDITS.rst
odoo/addons/website_megamenu/readme/DESCRIPTION.rst
odoo/addons/website_megamenu/readme/ROADMAP.rst
odoo/addons/website_megamenu/readme/USAGE.rst
odoo/addons/website_megamenu/static/description/icon.png
odoo/addons/website_megamenu/static/description/index.html
odoo/addons/website_megamenu/static/src/img/s_mega_menu_menu_image_menu.png
odoo/addons/website_megamenu/static/src/img/s_mega_menu_multi_menus.png
odoo/addons/website_megamenu/static/src/js/content.js
odoo/addons/website_megamenu/static/src/js/editor_menu.js
odoo/addons/website_megamenu/static/src/js/rte.js
odoo/addons/website_megamenu/static/src/js/snippets.editor.js
odoo/addons/website_megamenu/static/src/scss/website.scss
odoo/addons/website_megamenu/static/src/xml/website.contentMenu.xml
odoo/addons/website_megamenu/templates/assets.xml
odoo/addons/website_megamenu/templates/snippets.xml
odoo/addons/website_megamenu/templates/website.xml
odoo12_addon_website_megamenu-12.0.1.1.0.dist-info/METADATA
odoo12_addon_website_megamenu-12.0.1.1.0.dist-info/WHEEL
odoo12_addon_website_megamenu-12.0.1.1.0.dist-info/top_level.txt
odoo12_addon_website_megamenu-12.0.1.1.0.dist-info/RECORD
